find_best_string/__init__.py
find_best_string/main.py
find_best_string/utils.py
find_best_string-0.1.0.dist-info/METADATA
find_best_string-0.1.0.dist-info/RECORD
find_best_string-0.1.0.dist-info/WHEEL
find_best_string-0.1.0.dist-info/top_level.txt
