Metadata-Version: 2.1
Name: find-best-string
Version: 0.1.0
Summary: Finds the best matching string in a larger string.
Home-page: https://github.com/alexseitsinger/find_best_string
Author: Alex Seitsinger
Author-email: alexseitsinger@gmail.com
License: BSD 2-Clause License
Platform: UNKNOWN
Classifier: Development Status :: 3 - Alpha
Classifier: Intended Audience :: Developers
Classifier: License :: OSI Approved :: BSD License
Classifier: Programming Language :: Python
Classifier: Programming Language :: Python :: 3
Classifier: Programming Language :: Python :: 3.6
Classifier: Topic :: Text Processing :: General
Classifier: Topic :: Utilities
